rlbot_gui/__init__.py
rlbot_gui/gui.py
rlbot_gui/bot_management/__init__.py
rlbot_gui/bot_management/bot_creation.py
rlbot_gui/bot_management/downloader.py
rlbot_gui/gui/main.html
rlbot_gui/gui/css/appearance-editor.css
rlbot_gui/gui/css/bootstrap-vue.min.css
rlbot_gui/gui/css/bootstrap.min.css
rlbot_gui/gui/css/story.css
rlbot_gui/gui/css/style.css
rlbot_gui/gui/csv/items.csv
rlbot_gui/gui/imgs/arena_diagram.png
rlbot_gui/gui/imgs/epic.png
rlbot_gui/gui/imgs/human.png
rlbot_gui/gui/imgs/psyonix.png
rlbot_gui/gui/imgs/rlbot.png
rlbot_gui/gui/imgs/rlbot_logo.png
rlbot_gui/gui/imgs/steam.png
rlbot_gui/gui/imgs/arenas/AquaDome.jpg
rlbot_gui/gui/imgs/arenas/Arctagon.jpg
rlbot_gui/gui/imgs/arenas/Badlands.jpg
rlbot_gui/gui/imgs/arenas/Badlands_Night.jpg
rlbot_gui/gui/imgs/arenas/BeckwithPark.jpg
rlbot_gui/gui/imgs/arenas/BeckwithPark_GothamNight.jpg
rlbot_gui/gui/imgs/arenas/BeckwithPark_Midnight.jpg
rlbot_gui/gui/imgs/arenas/BeckwithPark_Stormy.jpg
rlbot_gui/gui/imgs/arenas/ChampionsField.jpg
rlbot_gui/gui/imgs/arenas/ChampionsField_Day.jpg
rlbot_gui/gui/imgs/arenas/ChampionsField_NFL.jpg
rlbot_gui/gui/imgs/arenas/Cosmic.jpg
rlbot_gui/gui/imgs/arenas/DFHStadium.jpg
rlbot_gui/gui/imgs/arenas/DFHStadium_Circuit.jpg
rlbot_gui/gui/imgs/arenas/DFHStadium_Day.jpg
rlbot_gui/gui/imgs/arenas/DFHStadium_Snowy.jpg
rlbot_gui/gui/imgs/arenas/DFHStadium_Stormy.jpg
rlbot_gui/gui/imgs/arenas/DeadeyeCanyon.jpg
rlbot_gui/gui/imgs/arenas/DoubleGoal.jpg
rlbot_gui/gui/imgs/arenas/DropShot_Core707.jpg
rlbot_gui/gui/imgs/arenas/Farmstead.jpg
rlbot_gui/gui/imgs/arenas/Farmstead_Night.jpg
rlbot_gui/gui/imgs/arenas/ForbiddenTemple.jpg
rlbot_gui/gui/imgs/arenas/ForbiddenTemple_Day.jpg
rlbot_gui/gui/imgs/arenas/Hoops_DunkHouse.jpg
rlbot_gui/gui/imgs/arenas/Mannfield.jpg
rlbot_gui/gui/imgs/arenas/Mannfield_Night.jpg
rlbot_gui/gui/imgs/arenas/Mannfield_Snowy.jpg
rlbot_gui/gui/imgs/arenas/Mannfield_Stormy.jpg
rlbot_gui/gui/imgs/arenas/NeoTokyo.jpg
rlbot_gui/gui/imgs/arenas/NeonFields.jpg
rlbot_gui-0.0.163.dist-info/METADATA
rlbot_gui-0.0.163.dist-info/WHEEL
rlbot_gui-0.0.163.dist-info/top_level.txt
rlbot_gui-0.0.163.dist-info/RECORD
