Metadata-Version: 2.4
Name: rlbot_gui
Version: 0.0.163
Summary: A streamlined user interface for RLBot.
Home-page: https://github.com/RLBot/RLBotGUI
Author: RLBot Community
Author-email: rlbotofficial@gmail.com
Keywords: rocket-league
Classifier: Programming Language :: Python :: 3
Classifier: License :: OSI Approved :: MIT License
Classifier: Operating System :: Microsoft :: Windows
Requires-Python: >=3.11
Requires-Dist: numba
Requires-Dist: scipy
Requires-Dist: numpy
Requires-Dist: RLUtilities
Requires-Dist: websockets
Requires-Dist: selenium
Requires-Dist: PyQt5
Dynamic: author
Dynamic: author-email
Dynamic: classifier
Dynamic: description
Dynamic: description-content-type
Dynamic: home-page
Dynamic: keywords
Dynamic: requires-dist
Dynamic: requires-python
Dynamic: summary
